rabbitai/__init__.py
rabbitai/cli.py
rabbitai/config_manager.py
rabbitai/logger.py
rabbitai/agents/__init__.py
rabbitai/agents/agent.py
rabbitai/agents/baseagent.py
rabbitai/agents/reactagent.py
rabbitai/command_config/__init__.py
rabbitai/command_config/os_commands.py
rabbitai/command_config/safety_patterns.py
rabbitai/context/__init__.py
rabbitai/context/system.py
rabbitai/llm/__init__.py
rabbitai/llm/base.py
rabbitai/llm/gemini.py
rabbitai/llm/ollama.py
rabbitai/tools/__init__.py
rabbitai/tools/executor.py
rabbitai-0.1.0.dist-info/METADATA
rabbitai-0.1.0.dist-info/WHEEL
rabbitai-0.1.0.dist-info/entry_points.txt
rabbitai-0.1.0.dist-info/top_level.txt
rabbitai-0.1.0.dist-info/RECORD
