Metadata-Version: 2.4
Name: rabbitai
Version: 0.1.0
Summary: AI-powered CLI troubleshooting assistant using ReAct pattern with LLM backends (Gemini/Ollama)
Author-email: Aritra777 <aritrabiswas.dev@gmail.com>
License: MIT
Project-URL: Homepage, https://github.com/Aritra777/rabbitai
Project-URL: Repository, https://github.com/Aritra777/rabbitai
Project-URL: Documentation, https://github.com/Aritra777/rabbitai#readme
Keywords: cli,troubleshooting,ai,llm,react,agent,gemini,ollama,langchain
Classifier: Development Status :: 3 - Alpha
Classifier: Intended Audience :: Developers
Classifier: Intended Audience :: System Administrators
Classifier: Topic :: Software Development
Classifier: Topic :: System :: Systems Administration
Classifier: License :: OSI Approved :: MIT License
Classifier: Programming Language :: Python :: 3
Classifier: Programming Language :: Python :: 3.9
Classifier: Programming Language :: Python :: 3.10
Classifier: Programming Language :: Python :: 3.11
Classifier: Programming Language :: Python :: 3.12
Classifier: Programming Language :: Python :: 3.13
Classifier: Environment :: Console
Classifier: Operating System :: OS Independent
Requires-Python: >=3.9
Requires-Dist: langchain<1.0.0,>=0.3.0
Requires-Dist: langgraph<1.0.0,>=0.2.0
Requires-Dist: langchain-google-genai<3.0.0,>=2.0.0
Requires-Dist: langchain-community>=0.3.0
Requires-Dist: prompt_toolkit>=3.0.52
Requires-Dist: rich>=14.2.0
Requires-Dist: pyyaml>=6.0.3
Provides-Extra: dev
Requires-Dist: pytest>=8.4.2; extra == "dev"
Requires-Dist: black>=25.9.0; extra == "dev"
Requires-Dist: flake8>=7.3.0; extra == "dev"
Requires-Dist: mypy>=1.18.2; extra == "dev"
